qsum/__init__.py
qsum/core/__init__.py
qsum/core/cache.py
qsum/core/constants.py
qsum/core/dependency.py
qsum/core/exceptions.py
qsum/core/logic.py
qsum/core/tests/__init__.py
qsum/core/tests/test_cache.py
qsum/core/tests/test_checksum_class.py
qsum/core/tests/test_dependency.py
qsum/core/tests/test_function_checksum.py
qsum/core/tests/test_logic.py
qsum/data/__init__.py
qsum/data/data_logic.py
qsum/data/data_type_map.py
qsum/data/to_bytes.py
qsum/data/to_bytes_custom.py
qsum/data/tests/__init__.py
qsum/data/tests/test_by_type.py
qsum/data/tests/test_data_logic.py
qsum/data/tests/test_specific_types.py
qsum/data/tests/test_to_bytes.py
qsum/data/tests/test_to_bytes_custom.py
qsum/examples/__init__.py
qsum/examples/basic_checksum.py
qsum/examples/checksum_performance.py
qsum/examples/combine_checksums.py
qsum/examples/inherited_container.py
qsum/examples/misc_checksums.py
qsum/examples/package_versions.py
qsum/examples/using_checksums.py
qsum/tests/__init__.py
qsum/tests/helpers.py
qsum/tests/test_structure.py
qsum/tools/__init__.py
qsum/tools/counting.py
qsum/types/__init__.py
qsum/types/type_logic.py
qsum/types/type_map.py
qsum/types/tests/__init__.py
qsum/types/tests/test_type_logic.py
qsum/types/tests/test_type_map.py
qsum/util/__init__.py
qsum/util/_tester.py
qsum-0.2.1.dist-info/LICENSE.txt
qsum-0.2.1.dist-info/METADATA
qsum-0.2.1.dist-info/WHEEL
qsum-0.2.1.dist-info/top_level.txt
qsum-0.2.1.dist-info/RECORD
